ez_setup.py
drafts/__init__.py
drafts/imagelist_coadd.py
drafts/rebuild_frame.py
drafts/test_fourierR.py
drafts/test_matching.py
drafts/test_proper_coadd.py
drafts/test_propercoad.py
drafts/test_propersubtract.py
drafts/test_psf_measure.py
drafts/test_real_coadd.py
drafts/test_realimage.py
drafts/test_recover_stats.py
drafts/test_simulated_psfs.py
drafts/test_sniptf.py
drafts/test_subtract_sniptf.py
drafts/test_variablepsf.py
drafts/test_varpsf_coadd.py
drafts/test_zpoint.py
properimage/__init__.py
properimage/combinator.py
properimage/image_ensemble.py
properimage/numpydb.py
properimage/operations.py
properimage/plot.py
properimage/propercoadd.py
properimage/propersubtract.py
properimage/simtools.py
properimage/single_image.py
properimage/single_image_psfs.py
properimage/utils.py
properimage/tests/__init__.py
properimage/tests/core.py
properimage/tests/run.py
properimage/tests/simtools.py
properimage/tests/test_combinator.py
properimage/tests/test_plot.py
properimage/tests/test_propercoadd.py
properimage/tests/test_propersubtract.py
properimage/tests/test_simtools.py
properimage/tests/test_single_image.py
properimage/tests/test_utils.py
properimage/tplibs/__init__.py
test/__init__.py
test/imagelist_coadd.py
test/rebuild_frame.py
test/test_fourierR.py
test/test_matching.py
test/test_proper_coadd.py
test/test_propercoad.py
test/test_propersubtract.py
test/test_psf_measure.py
test/test_real_coadd.py
test/test_realimage.py
test/test_recover_stats.py
test/test_simulated_psfs.py
test/test_sniptf.py
test/test_subtract_sniptf.py
test/test_variablepsf.py
test/test_varpsf_coadd.py
test/test_zpoint.py
tests/__init__.py
tests/conftest.py
tests/core.py
tests/test_combinator.py
tests/test_plot.py
tests/test_propercoadd.py
tests/test_propersubtract.py
tests/test_simtools.py
tests/test_single_image.py
tests/test_utils.py
properimage-0.7.1.dist-info/LICENSE.txt
properimage-0.7.1.dist-info/METADATA
properimage-0.7.1.dist-info/WHEEL
properimage-0.7.1.dist-info/pbr.json
properimage-0.7.1.dist-info/top_level.txt
properimage-0.7.1.dist-info/RECORD
