Metadata-Version: 2.1
Name: properimage
Version: 0.7.1
Summary: Proper Astronomic Image Analysis
Home-page: https://github.com/toros-astro/ProperImage
Author: Bruno Sanchez
Author-email: bruno@oac.unc.edu.ar
License: BSD 3
Keywords: astronomy image
Platform: UNKNOWN
Classifier: Development Status :: 4 - Beta
Classifier: Intended Audience :: Education
Classifier: Intended Audience :: Science/Research
Classifier: License :: OSI Approved :: BSD License
Classifier: Operating System :: OS Independent
Classifier: Programming Language :: Python
Classifier: Programming Language :: Python :: 3
Classifier: Programming Language :: Python :: 3.6
Classifier: Programming Language :: Python :: 3.7
Classifier: Programming Language :: Python :: 3.8
Classifier: Programming Language :: Python :: Implementation :: CPython
Classifier: Topic :: Scientific/Engineering
License-File: LICENSE.txt
Requires-Dist: numpy (>=1.13.2)
Requires-Dist: scipy (>=1.0)
Requires-Dist: astropy (>=2.0)
Requires-Dist: matplotlib
Requires-Dist: sep
Requires-Dist: astroscrappy (>=1.0.5)
Requires-Dist: astroalign (>=1.0.3)
Requires-Dist: tinynpydb (>=0.1)
Requires-Dist: pyFFTW (>=0.12)
